pyriksprot_tagger/__init__.py
pyriksprot_tagger/cwb.py
pyriksprot_tagger/resources/__init__.py
pyriksprot_tagger/resources/sparv/Makefile
pyriksprot_tagger/resources/sparv/__init__.py
pyriksprot_tagger/resources/sparv/speech_xml_config.yaml
pyriksprot_tagger/scripts/__init__.py
pyriksprot_tagger/scripts/other/fix-duplicate-subfolders.sh
pyriksprot_tagger/scripts/other/git-timesync
pyriksprot_tagger/scripts/other/git_update_mtime.sh
pyriksprot_tagger/scripts/other/move_empty_files.sh
pyriksprot_tagger/scripts/other/setup-pipeline
pyriksprot_tagger/scripts/other/snake-it.sh
pyriksprot_tagger/scripts/other/stanza-models.sh
pyriksprot_tagger/scripts/tag.py
pyriksprot_tagger/scripts/tag.sh
pyriksprot_tagger/scripts/tag_info.py
pyriksprot_tagger/scripts/update-timestamps
pyriksprot_tagger/taggers/__init__.py
pyriksprot_tagger/taggers/spacy2.py
pyriksprot_tagger/taggers/stanza_tagger.py
pyriksprot_tagger/utility.py
pyriksprot_tagger/workflow/Makefile
pyriksprot_tagger/workflow/README.md
pyriksprot_tagger/workflow/Snakefile
pyriksprot_tagger/workflow/__init__.py
pyriksprot_tagger/workflow/rules/__init__.py
pyriksprot_tagger/workflow/rules/__paths__.py
pyriksprot_tagger/workflow/rules/compute_frequency.smk
pyriksprot_tagger/workflow/rules/extract_speeches.smk
pyriksprot_tagger/workflow/rules/help.smk
pyriksprot_tagger/workflow/rules/tag_protocols.smk
pyriksprot_tagger/workflow/rules/update_repository.smk
pyriksprot_tagger-2024.6.2.dist-info/LICENSE
pyriksprot_tagger-2024.6.2.dist-info/METADATA
pyriksprot_tagger-2024.6.2.dist-info/WHEEL
pyriksprot_tagger-2024.6.2.dist-info/entry_points.txt
pyriksprot_tagger-2024.6.2.dist-info/RECORD
