Metadata-Version: 2.1
Name: pyriksprot-tagger
Version: 2024.6.2
Summary: Pipeline that tags pyriksprot Parla-Clarin XML files
Home-page: https://westac.se
License: Apache-2.0
Author: Roger Mähler
Author-email: roger.mahler@hotmail.com
Requires-Python: ==3.11.*
Classifier: License :: OSI Approved :: Apache Software License
Classifier: Operating System :: OS Independent
Classifier: Programming Language :: Python
Classifier: Programming Language :: Python :: 3
Classifier: Programming Language :: Python :: 3.11
Classifier: Topic :: Software Development
Requires-Dist: click
Requires-Dist: cookiecutter
Requires-Dist: dehyphen
Requires-Dist: loguru
Requires-Dist: nltk (>=3.8.1,<4.0.0)
Requires-Dist: pandas
Requires-Dist: pathvalidate (>=2.5.2,<3.0.0)
Requires-Dist: poetry (>=1.4.2,<2.0.0)
Requires-Dist: pygit2
Requires-Dist: pyriksprot (>=2024.6.1,<2025.0.0)
Requires-Dist: snakefmt
Requires-Dist: snakemake
Requires-Dist: stanza
Requires-Dist: torch[cuda] (>=2.0.1,<3.0.0)
Project-URL: Repository, https://github.com/welfare-state-analytics/pyriksprot_tagger
